setup.cfg
setup.py
filelogger/__init__.py
filelogger.egg-info/PKG-INFO
filelogger.egg-info/SOURCES.txt
filelogger.egg-info/dependency_links.txt
filelogger.egg-info/top_level.txt