Metadata-Version: 1.1
Name: filelogger
Version: 0.55
Summary: Wrapper class for RotatingFileHandler from logging module
Home-page: https://github.com/nickmetal/FileLogger
Author: Nickolai Morozov
Author-email: nickmetal92@gmail.com
License: UNKNOWN
Download-URL: https://github.com/nickmetal/filelogger/archive/0.55.tar.gz
Keywords: testing,logging
Platform: UNKNOWN
